{
  "seo": {
    "title": "Kompres PDF tetap mudah dibaca - Panduan browser",
    "description": "Kurangi ukuran PDF di browser sambil memeriksa keterbacaan, jumlah halaman, dan batas praktis."
  },
  "h1": "Kompres PDF tetap mudah dibaca",
  "lead": "Perkecil PDF harian dengan langkah peninjauan agar hasil tetap berguna untuk formulir, materi belajar, dan lampiran.",
  "strings": {
    "adLabel": "Iklan",
    "primaryToolRoute": "compress",
    "breadcrumbLabel": "Breadcrumb",
    "breadcrumbCurrent": "Kompres PDF tetap mudah dibaca",
    "heroEyebrow": "Kompresi dengan cek kualitas",
    "ctaEyebrow": "Mulai dengan hati-hati",
    "ctaTitle": "Kurangi ukuran tanpa melewati peninjauan",
    "ctaText": "Kompresi hanya berguna jika PDF akhir masih bisa dibaca. Gunakan alat, lalu periksa hasil sebelum mengirim.",
    "toolCardTitle": "Buka kompresor",
    "toolCardText": "Coba pembersihan struktur terlebih dahulu dan unduh hasil untuk pemeriksaan per halaman.",
    "primaryCta": "Kompres PDF",
    "stepsEyebrow": "Alur tinjauan",
    "stepsTitle": "Masukkan keterbacaan dalam proses",
    "stepsLead": "Anggap kompresi sebagai hasil sementara yang perlu diperiksa, bukan garis akhir otomatis.",
    "stepOneTitle": "Pilih file yang tepat",
    "stepOneText": "Gunakan PDF asli jika memungkinkan, bukan tangkapan layar atau pindaian ponsel yang disimpan ulang.",
    "stepTwoTitle": "Gunakan optimasi aman",
    "stepTwoText": "Jalankan alat browser dan simpan file sumber sampai Anda tahu hasilnya dapat diterima.",
    "stepThreeTitle": "Periksa hasil",
    "stepThreeText": "Perbesar teks kecil, tanda tangan, tabel, dan cap sebelum berbagi.",
    "limitationsEyebrow": "Batas jujur",
    "limitationsTitle": "Keterbacaan bergantung pada PDF asli",
    "limitationsText": "PDF berbasis teks biasanya bertahan lebih baik daripada pindaian resolusi rendah. Sebagian file perlu perubahan di sumber.",
    "limitationsItemOne": "Jika pindaian asli buram, kompresi tidak dapat mengembalikan detail.",
    "limitationsItemTwo": "Jika gambar mendominasi dokumen, pengurangan ukuran dapat berpengaruh pada kejelasan.",
    "limitationsItemThree": "Jika platform memiliki batas ukuran ketat, Anda mungkin perlu menghapus halaman atau mengekspor ulang dari sumber.",
    "privacyEyebrow": "Privasi",
    "privacyTitle": "Tinjau pemrosesan lokal browser",
    "privacyText": "Isi file dibaca oleh browser untuk tindakan alat. Aset situs, analitik, dan permintaan iklan biasa masih dapat dimuat.",
    "privacyItemOneTitle": "Tanpa akun",
    "privacyItemOneText": "Alat dirancang untuk pembersihan dokumen sekali jalan tanpa login.",
    "privacyItemTwoTitle": "Pastikan aturan kerja",
    "privacyItemTwoText": "Jika PDF berisi konten rahasia atau diatur, periksa apakah alat browser diperbolehkan dalam alur kerja Anda.",
    "relatedEyebrow": "Alat terkait",
    "relatedTitle": "Siapkan PDF yang lebih bersih",
    "relatedLead": "Hasil yang mudah dibaca juga dipengaruhi urutan halaman, halaman ekstra, dan persyaratan tujuan.",
    "relatedCompressTitle": "Kompres PDF",
    "relatedCompressText": "Kurangi ukuran sambil menjaga langkah peninjauan tetap terlihat.",
    "relatedUploadTitle": "Persiapan unggah PDF",
    "relatedUploadText": "Bandingkan ukuran file dan pratinjau hasil sebelum mengirim.",
    "relatedManageTitle": "Kelola halaman PDF",
    "relatedManageText": "Hapus halaman yang tidak perlu disertakan.",
    "relatedAction": "Buka alat",
    "faqEyebrow": "FAQ",
    "faqTitle": "Pertanyaan kompresi yang tetap terbaca",
    "faqOneQuestion": "Apakah kompresi bisa tanpa penurunan kualitas?",
    "faqOneAnswer": "Sebagian pembersihan struktur dapat mengurangi ukuran tanpa perubahan visual yang jelas, tetapi setiap hasil tetap perlu diperiksa karena PDF berbeda-beda.",
    "faqTwoQuestion": "PDF apa yang biasanya tetap terbaca?",
    "faqTwoAnswer": "PDF berbasis teks dan dokumen yang diekspor dari sumber asli biasanya lebih baik daripada pindaian penuh foto.",
    "faqThreeQuestion": "Apa yang harus dilakukan jika hasil terlihat lebih buruk?",
    "faqThreeAnswer": "Gunakan file asli, kurangi ukuran gambar di dokumen sumber, atau hapus halaman yang tidak perlu sebelum mencoba lagi."
  }
}
